<?xml version="1.0" encoding="UTF-8" standalone="yes"?>
<UI>
   <toolbar action="toolbar-group" text="MENU_TOOLS_TOOLSBAR_GROUP">
      <item action="groupEdition"/>
      <item action="groupEditionQuit"/>
   </toolbar>
   <!--<toolbar action="toolbar-pages-number" text="MENU_TOOLS_TOOLSBAR_PAGES_NUM">
      <item action="page-new"/>
      <separator/>
      <item action="page-button-select"/>
   </toolbar>-->
   <toolbar action="toolbar-pages" text="MENU_TOOLS_TOOLSBAR_PAGES">
      <item action="page-combo-select"/>
      <separator/>
      <item action="page-new"/>
   </toolbar>
   <toolbar action="toolbar-zoom" text="MENU_TOOLS_TOOLSBAR_ZOOM">
      <item action="zoom-combo-select"/>
      <item action="zoom-global"/>
   </toolbar>
   <toolbar action="toolbar-files" text="MENU_TOOLS_TOOLSBAR_IO">
      <item action="new"/>
      <item action="open"/>
      <item action="save"/>
      <item action="print"/>
      <item action="printPageFormat"/>
   </toolbar>
   <toolbar action="toolbar-undo" text="MENU_TOOLS_TOOLSBAR_UNDO">
      <item action="undo"/>
      <item action="redo"/>
   </toolbar>
   <toolbar action="toolbar-computation" text="MENU_TOOLS_TOOLSBAR_COMPUTATION">
      <item action="bddConfigAndAlbizia"/>
      <item action="albizia"/>
   </toolbar>
   <toolbar action="toolbar-edit" text="MENU_TOOLS_TOOLSBAR_EDIT">
      <item action="remove"/>
      <item action="cut"/>
      <item action="copy"/>
      <item action="paste"/>
      <item action="pasteAndRenum"/>
      <item action="refreshPage"/>
   </toolbar>
   <toolbar action="toolbar-align" text="MENU_TOOLS_TOOLSBAR_ALIGN">
      <item action="align-left"/>
      <item action="align-center"/>
      <item action="align-right"/>
      <separator/>
      <item action="align-top"/>
      <item action="align-middle"/>
      <item action="align-bottom"/>
   </toolbar>
   <menu text="MENU_FILE">
      <item action="new"/>
      <item action="newFromTemplate" />
      <item action="open"/>
      <item action="save"/>
      <item action="saveAs"/>
      <item action="saveAsTemplate" />
      <item action="anonymiser"/>
      <item action="sendMail" />
      <menu text="GLOBAL_EXPORT">
	    <item action="dagExport"/>
	    <item action="dagExportSimple"/>
	    <item action="dagExportObserved"/>
	    <item action="dagSimtree21"/>
	    <item action="openPSA"/>
      </menu>
      <item action="kb3" />
      <item action="close"/>
      <separator/>
      <item action="printPageFormat"/>
      <item action="print"/>
      <item action="saveToRtf"/>
      <!-- menu text="MENU_FILE_REPORT">
	    <item action="exportPDFXSL"/>
	    <item action="exportDBK"/>
	    <item action="exportAdvanced"/>
      </menu  -->
      <separator/>
      <item action="statistics"/>
      <item action="generalInfo"/>   
      <separator/>
      <item action="recentFile"/>
      <separator/>
      <item action="exit"/>
   </menu>
   <menu text="MENU_EDIT">
      <item action="undo"/>
      <item action="redo"/>
      <separator/>
      <item action="copy"/>
      <item action="cut"/>
      <item action="paste"/>
      <item action="pasteAndRenum"/>
      <item action="remove"/>
      <separator/>
      <item action="globalAction"/>
      <item action="selectAction"/>
      <separator/>
      <item action="glueCreate"/>
      <item action="glueDelete"/>
      <separator/>
      <item action="selectAll"/>
      <item action="selectNone"/>
      <item action="connexSelect"/>
      <item action="amontSelect"/>
      <item action="avalSelect"/>
      <separator/>
      <menu text="MENU_EDIT_AUTO_LAYOUT">
      	<item action="autoLayout"/>
      	<item action="autoLayoutAll"/>
      	<!-- <item action="pruneTree"/> -->
      </menu>
      <separator/>
      <item action="property"/>
   </menu>
   <menu text="MENU_TOOLS">
      <item action="page-new"/>
      <item action="page-administrator"/>
      <item action="changePage"/>
      <item action="increasePage"/>
      <item action="decreasePage"/>
      <item action="newPageSize"/>
      <item action="refreshPage"/>
      <separator/>
      <item action="reportNavigate"/>
      <item action="displayLogicalTree"/>
      <separator/>
      <menu text="MENU_TOOLS_ALIGN">
         <item action="align-left"/>
         <item action="align-center"/>
         <item action="align-right"/>
         <separator/>
         <item action="align-top"/>
         <item action="align-middle"/>
         <item action="align-bottom"/>
      </menu>
       <menu text="MENU_TOOLS_ALIGN2">
	      <item action="align-left2"/>
	      <item action="align-center2"/>
	      <item action="align-right2"/>
	      <separator/>
	      <item action="align-top2"/>
	      <item action="align-middle2"/>
	      <item action="align-bottom2"/>
   	  </menu>
      <item action="raise"/>
      <item action="lower"/>
      <separator/>
      <menu text="MENU_TOOLS_TOOLSBAR">
         <item action="toolbar-pages"/>
         <!--<item action="toolbar-pages-number"/>-->
         <item action="toolbar-files"/>
         <item action="toolbar-undo"/>
         <item action="toolbar-edit"/>
         <item action="toolbar-align"/>
         <item action="toolbar-zoom"/>
         <item action="toolbar-group"/>
      </menu>
      <item action="drawStateBar"/>
      <item action="drawToggleBar"/>
	  	<item action="optionsDoc"/>
	  	<item action="optionsAppl"/>
   </menu>
   <menu text="MENU_DOC">
      <item action="next-doc"/>
      <item action="previous-doc"/>
      <separator/>
      <item action="currentDoc"/>
   </menu>
   <menu text="MENU_NET">
      <item action="tools"/>
   </menu>
   <menu text="MENU_DATA_AND_COMPUTE">
      <item action="csts"/>
      <item action="event"/>
<!--       <item action="atts"/> -->
      <item action="cleanData"/>
	  <separator/>
      <menu text="MENU_DATA_AND_COMPUTE_BDD">
         <item action="bddCSV"/>
      	 <item action="bddUpdate"/>
         <item action="bddCopy"/>
      </menu>
      <separator/>
      <item action="invalidateComputationCash"/>
      <item action="unique"/>
      <item action="verify"/>
      <separator/>
      <item action="markovPreproc"/>
      <item action="markovPreprocForced"/>
      <item action="bddConfigAndAlbizia"/>
      <item action="albizia"/>
	  <separator/>
      <item action="displayca"/>
      <menu text="MENU_DATA_AND_COMPUTE_BATCH_MENU">
      	 <item action="batch"/>
         <item action="autobatch"/>
      </menu>
  	  <separator/>
      <item action="configAndMoca"/>
      <item action="moca"/>
       <separator/>
       <item action="computeTargets"/>
      

   </menu>
   <menu text="MENU_GROUP">
      <item action="grouping"/>
      <item action="groupnew"/>
      <item action="groupChangeName"/>
      <item action="groupImage"/>
      <item action="ungrouping"/>
      <item action="groupSubSystem"/>
      <separator/>
      <item action="groupEdition"/>
      <item action="groupEditionQuit"/>
   </menu>
   <menu text="MENU_HELP">
	<item action="about" />
	<item action="help" />
	<item action="sendLogs" />
	<separator />
		<item action="languageFR" />
		<item action="languageEN" />
   </menu>
	<hide text="MENU_DEBUG" key="shift ctrl alt D">
		<item action="garbageCollector"/>  
		<item action="test"/>
		<item action="dagExport"/>
		<item action="exportEMF"/>
   </hide>
</UI>
